clrxdisasm_wrapper/__about__.py
clrxdisasm_wrapper/__init__.py
clrxdisasm_wrapper/__main__.py
clrxdisasm_wrapper/clrxdisasm_utils.py
clrxdisasm_wrapper/elf_utils.py
clrxdisasm_wrapper/kernel_descriptor.py
clrxdisasm_wrapper/metadata.py
clrxdisasm_wrapper/output_generator.py
clrxdisasm_wrapper/utils.py
clrxdisasm_wrapper-0.0.1.dist-info/METADATA
clrxdisasm_wrapper-0.0.1.dist-info/WHEEL
clrxdisasm_wrapper-0.0.1.dist-info/licenses/LICENSE.txt
clrxdisasm_wrapper-0.0.1.dist-info/RECORD
