Metadata-Version: 2.1
Name: clrxdisasm-wrapper
Version: 0.0.1
Summary: clrxdisasm wrapper for code object V4 support
Project-URL: Documentation, https://github.com/RubyUmbra/clrxdisasm-wrapper-py#readme
Project-URL: Issues, https://github.com/RubyUmbra/clrxdisasm-wrapper-py/issues
Project-URL: Source, https://github.com/RubyUmbra/clrxdisasm-wrapper-py
Author-email: "Dmitry \"RubyUmbra\" Gromov" <rubyumbra@gmail.com>
License-Expression: MIT
License-File: LICENSE.txt
Classifier: Development Status :: 4 - Beta
Classifier: Programming Language :: Python
Classifier: Programming Language :: Python :: 3.7
Classifier: Programming Language :: Python :: 3.8
Classifier: Programming Language :: Python :: 3.9
Classifier: Programming Language :: Python :: 3.10
Classifier: Programming Language :: Python :: 3.11
Requires-Python: >=3.7
Requires-Dist: argparse~=1.4.0
Requires-Dist: construct~=2.10.68
Requires-Dist: ormsgpack~=1.2.5
Requires-Dist: pyelftools~=0.29
